ut_arr/__init__.py
ut_arr/__version__.py
ut_arr/ao2a.py
ut_arr/aoa.py
ut_arr/aoo.py
ut_arr/aos.py
ut_arr/arr.py
ut_arr/py.typed
ut_arr/docs/Logging.rst
ut_arr/docs/README.rst
ut_arr/docs/Terminology.rst
ut_arr-2.0.0.20251020.dist-info/licenses/LICENSE.txt
ut_arr-2.0.0.20251020.dist-info/METADATA
ut_arr-2.0.0.20251020.dist-info/WHEEL
ut_arr-2.0.0.20251020.dist-info/top_level.txt
ut_arr-2.0.0.20251020.dist-info/RECORD
